README.md
setup.cfg
setup.py
PyEspecLib/__init__.py
PyEspecLib/models.py
PyEspecLib.egg-info/PKG-INFO
PyEspecLib.egg-info/SOURCES.txt
PyEspecLib.egg-info/dependency_links.txt
PyEspecLib.egg-info/requires.txt
PyEspecLib.egg-info/top_level.txt