Metadata-Version: 2.1
Name: PyEspecLib
Version: 0.0.2
Summary: Serial control lib for Programmable Temperature Chamer from espec.com
Home-page: https://github.com/lifetyper/PyEspecLib
Author: Bi Qin
Author-email: leavic@gmail.com
License: MIT
Keywords: serial control temperature chamber
Platform: UNKNOWN
Classifier: Development Status :: 3 - Alpha
Classifier: Intended Audience :: Developers
Classifier: Topic :: Software Development :: Build Tools
Classifier: License :: OSI Approved :: MIT License
Classifier: Programming Language :: Python :: 3.8
